cognite/logger/__init__.py
cognite/logger/logger.py
cognite/logger/py.typed
cognite_logger-0.6.0.dist-info/LICENSE
cognite_logger-0.6.0.dist-info/METADATA
cognite_logger-0.6.0.dist-info/WHEEL
cognite_logger-0.6.0.dist-info/RECORD
